Workbook

Sheet 参数
A2: 经营参数（改浅蓝格，其余表自动重算）
A3: 参数 | B3: 值 | E3: 说明
A4: 年产量（吨） | B4: 3000 | E4: 与 00-config 通用 profile 一致
A5: 出厂均价（元/吨） | B5: 28000 | E5: 按产品结构加权
A6: 营业收入（元） | B6: =B4*B5 -> 0 | E6: = 年产量 × 均价
A7: 原粮+曲种占比 | B7: 0.42 | E7: 占营业收入比，含损耗
A8: 包材占比 | B8: 0.1 | E8: 瓶、盖、标、箱
A9: 能耗占比 | B9: 0.021 | E9: 约 180 万/年
A10: 人工占比 | B10: 0.12 | E10: 生产与管理
A11: 制造费用占比 | B11: 0.06 | E11: 折旧、维修、坛损
A12: 坛储在库（吨） | B12: 300 | E12: 用于坛储损耗收益
A13: 平均库存金额（元） | B13: 3200000 | E13: 原粮+在制+成品
A14: 资金成本率 | B14: 0.02 | E14: 年化，保守取值
A15: 财务人员年成本（元/人） | B15: 80000 | E15: 与 13 分册一致
A16: 客服人员年成本（元/人） | B16: 60000 | E16: 与 13 分册一致
A17: 库存周转天数基线（天） | B17: 68 | E17: 见 00-config 指标基线
A19: AI 改善幅度（首年保守口径，低/中/高 = 0.5 / 1.0 / 2.0 倍）
A20: 改善项 | B20: 低 | C20: 中 | D20: 高 | E20: 说明
A21: 出酒率提升（对营收等效） | B21: 0.005 | C21: 0.01 | D21: 0.02 | E21: 每 1pt 约等效 +1% 营收
A22: 单位能耗下降 | B22: 0.025 | C22: 0.05 | D22: 0.1 | E22: 蒸汽与电耗优化
A23: 坛储损耗率下降 | B23: 0.004 | C23: 0.008 | D23: 0.016 | E23: 2.6% -> 1.8%
A24: 库存周转天数下降 | B24: 6 | C24: 13 | D24: 26 | E24: 68 -> 55 / 50 天
A25: 财务对账人力节省比例 | B25: 0.2 | C25: 0.4 | D25: 0.6 | E25: 2 人 × 比例
A26: 客服人力节省比例 | B26: 0.2 | C26: 0.4 | D26: 0.6 | E26: 1.5 人 × 比例
A27: 标签/证照返工规避（元） | B27: 50000 | C27: 100000 | D27: 200000 | E27: 避免下架返工
A28: 优质品率提升（对营收等效） | B28: 0.01 | C28: 0.02 | D28: 0.04 | E28: 81% -> 84% / 88%

Sheet 投资明细
A2: 投资分项（单位：万元）——与 13-路线图与ROI.md 第 3 节同源
A3: 阶段 | B3: 项目 | C3: 金额 | D3: 说明
A4: P0 | B4: 数字化专员 1 人（2 个月） | C4: 3 | D4: 内部人力，按年 18 万计
A5: P0 | B5: 编码与模板改造、数据清洗支持 | C5: 2 | D5: 外部顾问 5 人天
A6: P0 | B6: 打印/标签/单据耗材 | C6: 0.5 | D6: FB 号条码化
A7: P0 | B7: 数据质量监控脚本与看板 | C7: 2.5 | D7: 外部开发 6 人天
A8: P1 | B8: 温度采集试点（10 罐） | C8: 6 | D8: 约 0.6 万/罐
A9: P1 | B9: 化验室 LIMS-lite | C9: 3 | D9: 化验录入、批次绑定
A10: P1 | B10: 便携快检器具 | C10: 2 | D10: 折光仪、pH 计、电子秤
A11: P1 | B11: ERP/Excel 数据集成 | C11: 5 | D11: 中间库/视图 12 人天
A12: P1 | B12: Agent 平台（本地编排+审计日志） | C12: 4 | D12: 部署与配置
A13: P1 | B13: 首批 3 个 Agent 实施 | C13: 8 | D13: 标签审核、对账、票据
A14: P1 | B14: 云 API 与算力（4 个月） | C14: 1 | D14: 仅非敏感任务
A15: P1 | B15: 培训与手册 | C15: 1.5 | D15: 分岗位培训
... A20: P2 | B20: 客服与一物一码 | C20: 8 | D20: 编码、验真、知识库
A21: P2 | B21: 算力与云 API（6 个月） | C21: 2
A22: P2 | B22: 运营人力（第 2 人） | C22: 3 | D22: 内部人力
A23: P3 | B23: 本地 GPU 推理服务器 | C23: 15 | D23: 32B 级量化推理
A24: P3 | B24: 私有化模型部署与调优 | C24: 6 | D24: S3 数据本地推理
A25: P3 | B25: 视觉质检试点（1 条线） | C25: 12 | D25: 相机+光源+边缘盒
A26: P3 | B26: 批次成本与经营驾驶舱 | C26: 10 | D26: 指标 API + 问答
A27: P3 | B27: 能耗计量补点 | C27: 6 | D27: 分摊到批次成本
A28: P3 | B28: 算力与运维 | C28: 3
B29: 合计 | C29: =SUM(C4:C29) -> 0 | D29: 应为 141.5
B30: P0 小计 | C30: =SUMIF(A4:A29,"P0",C4:C29) -> 0 | D30: 8.0
B31: P1 小计 | C31: =SUMIF(A4:A29,"P1",C4:C29) -> 0 | D31: 33.5
B32: P2 小计 | C32: =SUMIF(A4:A29,"P2",C4:C29) -> 0 | D32: 48.0
B33: P3 小计 | C33: =SUMIF(A4:A29,"P3",C4:C29) -> 0 | D33: 52.0

Sheet 收益测算
A2: 首年收益测算（元）——公式驱动，改参数表即重算
A3: 收益项 | B3: 低 | C3: 中 | D3: 高 | E3: 计算口径
A4: 出酒率提升 | B4: =参数!B6*参数!B21 -> 0 | C4: =参数!B6*参数!C21 -> 0 | D4: =参数!B6*参数!D21 -> 0 | E4: 营收 × 提升幅度
A5: 单位能耗下降 | B5: =参数!B6*参数!B9*参数!B22 -> 0 | C5: =参数!B6*参数!B9*参数!C22 -> 0 | D5: =参数!B6*参数!B9*参数!D22 -> 0 | E5: 营收 × 能耗占比 × 降幅
A6: 坛储损耗下降 | B6: =参数!B13*参数!B5*参数!B23 -> 0 | C6: =参数!B13*参数!B5*参数!C23 -> 0 | D6: =参数!B13*参数!B5*参数!D23 -> 0 | E6: 坛储吨 × 均价 × 降幅
A7: 库存资金占用下降 | B7: =参数!B15*参数!B14*(参数!B24/参数!B18) -> 0 | C7: =参数!B15*参数!B14*(参数!C24/参数!B18) -> 0 | D7: =参数!B15*参数!B14*(参数!D24/参数!B18) -> 0 | E7: 库存 × 资金成本 × 周转加速
A8: 财务对账人力节省 | B8: =2*参数!B16*参数!B25 -> 0 | C8: =2*参数!B16*参数!C25 -> 0 | D8: =2*参数!B16*参数!D25 -> 0 | E8: 2 人 × 年成本 × 比例
A9: 客服人力节省 | B9: =1.5*参数!B17*参数!B26 -> 0 | C9: =1.5*参数!B17*参数!C26 -> 0 | D9: =1.5*参数!B17*参数!D26 -> 0 | E9: 1.5 人 × 年成本 × 比例
A10: 标签与证照返工规避 | B10: =参数!B27 -> 0 | C10: =参数!C27 -> 0 | D10: =参数!D27 -> 0 | E10: 直接取值
A11: 优质品率提升 | B11: =参数!B6*参数!B28 -> 0 | C11: =参数!B6*参数!C28 -> 0 | D11: =参数!B6*参数!D28 -> 0 | E11: 营收 × 提升幅度
A12: 首年收益合计 | B12: =SUM(B4:B11) -> 0 | C12: =SUM(C4:C11) -> 0 | D12: =SUM(D4:D11) -> 0 | E12: 元/年
A14: 三年口径
A15: 项目 | B15: 低 | C15: 中 | D15: 高 | E15: 说明
A16: 第 1 年收益 | B16: =B12 -> 0 | C16: =C12 -> 0 | D16: =D12 -> 0 | E16: 同首年测算
A17: 第 2 年收益（×2.0） | B17: =B15*2 -> 0 | C17: =C15*2 -> 0 | D17: =D15*2 -> 0 | E17: 规模效应与场景扩面
A18: 第 3 年收益（×2.5） | B18: =B15*2.5 -> 0 | C18: =C15*2.5 -> 0 | D18: =D15*2.5 -> 0 | E18: 成本精细化与排产优化
A19: 三年收益合计 | B19: =SUM(B15:B17) -> 0 | C19: =SUM(C15:C17) -> 0 | D19: =SUM(D15:D17) -> 0 | E19: 元
A20: 三年投入（万元） | B20: 141.5 | C20: 141.5 | D20: 141.5 | E20: 见投资明细合计
A21: 投入产出比 | B21: =B18/(B19*10000) -> 0 | C21: =C18/(C19*10000) -> 0 | D21: =D18/(D19*10000) -> 0 | E21: >1 即回本
A22: 回收期（月） | B22: =B19*10000/(B15/12) -> 0 | C22: =C19*10000/(C15/12) -> 0 | D22: =D19*10000/(D15/12) -> 0 | E22: 按首年收益折算

Sheet 说明
A1: 使用说明
A2: 1. 本表是《米酒厂 AI 管理体系》配套测算工具，与 13-路线图与ROI.md 数字同源。
A3: 2. 只改“参数”表浅蓝底色单元格，“收益测算”表自动重算；公式为静态文本，Excel/WPS 打开即生效。
A4: 3. 低/中/高三档 = 首年改善幅度的 0.5 / 1.0 / 2.0 倍，用于给立项决策留区间。
A5: 4. 收益为量级估算，未含停产改造损失、人员学习成本与第 2 年起的运维（约 6–10 万/年）。
A6: 5. 出厂均价与各成本占比须按本厂实际财务数据替换后，再用于正式立项决策。
A7: 6. 生成方式：node tools/build-estimate-model.mjs（纯 Node 标准库，无需安装依赖）。
